OrderedSet.py
PrettyTable.py
XiaoweiJob.py
XiaoweiLib.py
XiaoweiTask.py
XiaoweiLib-1.2.8.dist-info/LICENSE
XiaoweiLib-1.2.8.dist-info/METADATA
XiaoweiLib-1.2.8.dist-info/WHEEL
XiaoweiLib-1.2.8.dist-info/top_level.txt
XiaoweiLib-1.2.8.dist-info/RECORD
